zhongzhi_mcp/__init__.py
zhongzhi_mcp/auth.py
zhongzhi_mcp/client.py
zhongzhi_mcp/config.py
zhongzhi_mcp/server.py
zhongzhi_mcp-0.1.3.dist-info/METADATA
zhongzhi_mcp-0.1.3.dist-info/WHEEL
zhongzhi_mcp-0.1.3.dist-info/entry_points.txt
zhongzhi_mcp-0.1.3.dist-info/top_level.txt
zhongzhi_mcp-0.1.3.dist-info/RECORD
