Metadata-Version: 2.4
Name: zhongzhi-mcp
Version: 0.1.3
Summary: MCP server for Zhongzhi (IPPH) API
Requires-Python: >=3.10
Requires-Dist: mcp
Requires-Dist: httpx
Requires-Dist: python-dotenv
